ugrad/__init__.py
ugrad/init.py
ugrad/tensor.py
ugrad/nn/__init__.py
ugrad/nn/functional.py
ugrad/nn/module.py
ugrad/optim/__init__.py
ugrad/optim/lr_scheduler.py
ugrad/optim/optimizer.py
ugrad/test/__init__.py
ugrad/test/test_model.py
ugrad/test/test_ugrad.py
ugrad-0.1.0.dist-info/LICENSE
ugrad-0.1.0.dist-info/METADATA
ugrad-0.1.0.dist-info/WHEEL
ugrad-0.1.0.dist-info/top_level.txt
ugrad-0.1.0.dist-info/RECORD
